wgcapture/__init__.py
wgcapture/__main__.py
wgcapture/core.py
wgcapture/dlls/wgc_core.dll
wgcapture-0.1.2.dist-info/licenses/LICENSE
wgcapture-0.1.2.dist-info/METADATA
wgcapture-0.1.2.dist-info/WHEEL
wgcapture-0.1.2.dist-info/top_level.txt
wgcapture-0.1.2.dist-info/RECORD
