Metadata-Version: 2.4
Name: wgcapture
Version: 0.1.2
Summary: "Simple window specific sreengrab using Windows Graphics Capture"
Author: Zongyu Carnes
License: MIT
Classifier: Programming Language :: Python :: 3
Classifier: Operating System :: Microsoft :: Windows
Classifier: License :: OSI Approved :: MIT License
License-File: LICENSE
Requires-Dist: numpy
Requires-Dist: Pillow
Requires-Dist: pygetwindow
Dynamic: license-file
